eventually/__init__.py
eventually/_deprecate.py
eventually/_version.py
eventually/test/__init__.py
eventually/test/_deprecatetests.py.3only
eventually/test/test_deprecate.py
eventually-17.3.0.dist-info/DESCRIPTION.rst
eventually-17.3.0.dist-info/METADATA
eventually-17.3.0.dist-info/metadata.json
eventually-17.3.0.dist-info/RECORD
eventually-17.3.0.dist-info/top_level.txt
eventually-17.3.0.dist-info/WHEEL
