Metadata-Version: 2.0
Name: eventually
Version: 17.3.0
Summary: Deprecation support for Python.
Home-page: https://github.com/twisted/eventually
Author: Amber Brown
Author-email: hawkowl@twistedmatrix.com
License: MIT
Platform: UNKNOWN
Classifier: Intended Audience :: Developers
Classifier: License :: OSI Approved :: MIT License
Classifier: Programming Language :: Python :: 2
Classifier: Programming Language :: Python :: 2.7
Classifier: Programming Language :: Python :: 3
Classifier: Programming Language :: Python :: 3.3
Classifier: Programming Language :: Python :: 3.4
Classifier: Programming Language :: Python :: 3.5
Classifier: Programming Language :: Python :: 3.6
Requires-Dist: incremental
